interactive_classification_metrics/.gitignore
interactive_classification_metrics/LICENSE
interactive_classification_metrics/README.md
interactive_classification_metrics/__init__.py
interactive_classification_metrics/distributions.py
interactive_classification_metrics/metrics.py
interactive_classification_metrics/requirements.txt
interactive_classification_metrics/run_app.py
interactive_classification_metrics/serve.py
interactive_classification_metrics-0.2.2.dist-info/METADATA
interactive_classification_metrics-0.2.2.dist-info/WHEEL
interactive_classification_metrics-0.2.2.dist-info/entry_points.txt
interactive_classification_metrics-0.2.2.dist-info/licenses/LICENSE
interactive_classification_metrics-0.2.2.dist-info/RECORD
